campuspulse_event_ingest_schema/__init__.py
campuspulse_event_ingest_schema/common.py
campuspulse_event_ingest_schema/events.py
campuspulse_event_ingest_schema-0.1.0.dist-info/LICENSE
campuspulse_event_ingest_schema-0.1.0.dist-info/METADATA
campuspulse_event_ingest_schema-0.1.0.dist-info/WHEEL
campuspulse_event_ingest_schema-0.1.0.dist-info/top_level.txt
campuspulse_event_ingest_schema-0.1.0.dist-info/RECORD
