Metadata-Version: 2.1
Name: campuspulse-event-ingest-schema
Version: 0.1.0
Summary: Normalized data schema for the output of the data-ingest pipeline.
Home-page: https://github.com/CampusPulse/event-data-schema
Author: Adrian Edwards
License: MIT
Project-URL: Issues, https://github.com/CampusPulse/event-data-schema/issues
Project-URL: CI, https://github.com/CampusPulse/event-data-schema/actions
Project-URL: Changelog, https://github.com/CampusPulse/event-data-schema/releases
Requires-Python: >=3.8
License-File: LICENSE
Requires-Dist: pydantic[email] ~=1.10
Provides-Extra: lint
Requires-Dist: flake8 ; extra == 'lint'
Requires-Dist: black ; extra == 'lint'
Requires-Dist: mypy ; extra == 'lint'
Requires-Dist: isort ; extra == 'lint'
Provides-Extra: test
Requires-Dist: pytest ; extra == 'test'
